__init__.py
pyvider/__init__.py
pyvider/telemetry/__init__.py
pyvider/telemetry/config.py
pyvider/telemetry/core.py
pyvider/telemetry/py.typed
pyvider/telemetry/semantic_layers.py
pyvider/telemetry/types.py
pyvider/telemetry/utils.py
pyvider/telemetry/logger/__init__.py
pyvider/telemetry/logger/base.py
pyvider/telemetry/logger/custom_processors.py
pyvider/telemetry/logger/emoji_matrix.py
pyvider_telemetry-0.0.16.dist-info/licenses/LICENSE
pyvider_telemetry-0.0.16.dist-info/METADATA
pyvider_telemetry-0.0.16.dist-info/WHEEL
pyvider_telemetry-0.0.16.dist-info/top_level.txt
pyvider_telemetry-0.0.16.dist-info/RECORD
