Metadata-Version: 2.4
Name: pyvider-telemetry
Version: 0.0.16
Summary: Pyvider Telemetry: An opinionated, developer-friendly telemetry wrapper for Python.
Author-email: Tim Perkins <code@tim.life>
Maintainer-email: "provide.io" <code@provide.io>
License: Apache-2.0
Project-URL: Homepage, https://pyvider.com/
Project-URL: Repository, https://github.com/provider-io/pyvider-telemetry
Keywords: telemetry,logging,tracing,python,pyvider
Classifier: Development Status :: 3 - Alpha
Classifier: Intended Audience :: Developers
Classifier: License :: OSI Approved :: Apache Software License
Classifier: Operating System :: OS Independent
Classifier: Programming Language :: Python :: 3.11
Classifier: Programming Language :: Python :: 3.12
Classifier: Programming Language :: Python :: 3.13
Classifier: Programming Language :: Python :: 3.14
Classifier: Topic :: System :: Logging
Classifier: Topic :: System :: Monitoring
Classifier: Topic :: Software Development :: Libraries :: Python Modules
Classifier: Typing :: Typed
Requires-Python: >=3.11
License-File: LICENSE
Requires-Dist: attrs>=23.1.0
Requires-Dist: structlog>=25.3.0
Provides-Extra: opentelemetry
Requires-Dist: opentelemetry-api>=1.22.0; extra == "opentelemetry"
Requires-Dist: opentelemetry-sdk>=1.22.0; extra == "opentelemetry"
Requires-Dist: opentelemetry-exporter-otlp-proto-grpc>=1.22.0; extra == "opentelemetry"
Requires-Dist: opentelemetry-exporter-otlp-proto-http>=1.22.0; extra == "opentelemetry"
Dynamic: license-file
